queryshield_monitoring/__init__.py
queryshield_monitoring/django_middleware.py
queryshield_monitoring/fastapi_middleware.py
queryshield_monitoring/middleware.py
queryshield_monitoring-0.2.0.dist-info/METADATA
queryshield_monitoring-0.2.0.dist-info/WHEEL
queryshield_monitoring-0.2.0.dist-info/RECORD
